[
  {
    "id": "757",
    "name": "6, ул. Николая Василенко, 2 (метро Берестейская)"
  },
  {
    "id": "865",
    "name": "60, ул. Днепровская набережная, 26и (м. Осокорки)"
  },
  {
    "id": "867",
    "name": "61, просп. Лобановского, 3"
  },
  {
    "id": "869",
    "name": "62, просп. Григоренко, 22/20"
  },
  {
    "id": "871",
    "name": "63, ул. Набережно-Хрещатицкая, 15-17/18"
  },
  {
    "id": "87319",
    "name": "65, ул. Анри Барбюса, 53, пом. 1140"
  },
  {
    "id": "877",
    "name": "66, ул. Сирецкая, 9 (Куреневка)"
  },
  {
    "id": "879",
    "name": "67, ул. К. Данькевича, 16 (Троещина)"
  },
  {
    "id": "881",
    "name": "68, ул. Бориса Гмыри, 1 (м. Позняки)"
  },
  {
    "id": "883",
    "name": "69, ул. Лаврухина, 3"
  },
  {
    "id": "122276",
    "name": "6000, Почтомат Новая Почта №6000 просп. Маяковского Владимира, 89б (маг. АТБ)"
  },
  {
    "id": "122277",
    "name": "6002, Почтомат Новая Почта №6002 ул. Русановская Набережная, 18 (маг. АТБ)"
  },
  {
    "id": "122278",
    "name": "6003, Почтомат Новая Почта №6003 Харьковское шоссе, 201 (маг. АТБ)"
  },
  {
    "id": "122279",
    "name": "6004, Почтомат Новая Почта №6004 ул. Архитектора Николаева, 7 (маг. АТБ)"
  },
  {
    "id": "122281",
    "name": "6018, Почтомат Новая Почта №6018 ул. Академика Заболотного, 37 (ТЦ АртМолл)"
  },
  {
    "id": "122282",
    "name": "6019, Почтомат Новая Почта №6019 с. С. Борщаговка, ул. Оксамитовая, 1/1 (Минимаркет)"
  },
  {
    "id": "122283",
    "name": "6020, Почтомат Новая Почта №6020 ул. Кириловская, 126/2 (маг. Щедрый Кошик)"
  },
  {
    "id": "122284",
    "name": "6021, Почтомат Новая Почта №6021 ул. Урловская, 30 (ОкейМаркет)"
  },
  {
    "id": "122285",
    "name": "6022, Почтомат Новая Почта №6022 с. ПП Борщ., ул. Школьная, 10 (Минимаркет)"
  },
  {
    "id": "122286",
    "name": "6023, Почтомат Новая Почта №6023 ул. Рыбальская, 22 (БЦ Башта)"
  },
  {
    "id": "122287",
    "name": "6024, Почтомат Новая Почта №6024 метро Льва Толстого (маг. Продмаг)"
  },
  {
    "id": "122288",
    "name": "6026, Почтомат Новая Почта №6026 ул. Костельная, 3 (маг. Продмаг)"
  },
  {
    "id": "122289",
    "name": "6027, Почтомат Новая Почта №6027 ул. Щусева, 32 (маг. Фудмаркет)"
  },
  {
    "id": "122290",
    "name": "6028, Почтомат Новая Почта №6028 бульв. Леси Украинки, 36/10 (маг. Делви)"
  },
  {
    "id": "122291",
    "name": "6029, Почтомат Новая Почта №6029 ул. Волынская, 16 (маг. Делви)"
  },
  {
    "id": "122292",
    "name": "6030, Почтомат Новая Почта №6030 Харьковское шоссе, 21/4 (маг. Делви)"
  },
  {
    "id": "122421",
    "name": "6031, Почтомат Новая Почта №6031 ул. Святошинская, 4 (маг. АТБ)"
  },
  {
    "id": "122422",
    "name": "6032, Почтомат Новая Почта №6032 ул. Эрнста, 14 (маг. АТБ)"
  },
  {
    "id": "122423",
    "name": "6033, Почтомат Новая Почта №6033 ул. Архитектора Вербицкого, 1 (маг. АТБ)"
  },
  {
    "id": "122424",
    "name": "6034, Почтомат Новая Почта №6034 просп. Леся Курбаса, 1а (маг. АТБ)"
  },
  {
    "id": "122462",
    "name": "6054, Почтомат Новая Почта №6054 ул. Днепровская набережная, 7 (маг. АТБ)"
  },
  {
    "id": "122893",
    "name": "6059, Почтомат Новая Почта №6059 ул. Уссурийская, 11 (маг. Минимаркет)"
  },
  {
    "id": "122894",
    "name": "6060, Почтомат Новая Почта №6060 ул. Борщаговская, 152 (маг. Минимаркет)"
  },
  {
    "id": "122895",
    "name": "6061, Почтомат Новая Почта №6061 ул. Иллинская, 8 (БЦ Ильинский)"
  },
  {
    "id": "123393",
    "name": "6146, Почтомат Новая Почта №6146 ул. Большая Васильковская, 120 (Отделение №75)"
  },
  {
    "id": "123725",
    "name": "6148, Почтомат Новая Почта №6148 ул. Алматинская, 2/1 (маг. АТБ)"
  },
  {
    "id": "124679",
    "name": "6158, Почтомат Новая Почта №6158 переул. Карельский, 7/2 (БРСМ-Нефть)"
  },
  {
    "id": "123628",
    "name": "6161, Почтомат Новая Почта №6161 просп. Науки, 49а (WOG)"
  },
  {
    "id": "124680",
    "name": "6163, Почтомат Новая Почта №6163 ул. Алматинская, 105/2 (маг. Лоток)"
  },
  {
    "id": "123629",
    "name": "6164, Почтомат Новая Почта №6164 ул. Васильковская, 42а (маг. Лоток)"
  },
  {
    "id": "123630",
    "name": "6165, Почтомат Новая Почта №6165 ул. Лятошинского, 24а (маг. Лоток)"
  },
  {
    "id": "123631",
    "name": "6166, Почтомат Новая Почта №6166 ул. Оболонская, 35 (маг. Лоток)"
  },
  {
    "id": "124681",
    "name": "6167, Почтомат Новая Почта №6167 ул. Ревуцкого, 42в (маг. Лоток)"
  },
  {
    "id": "123632",
    "name": "6168, Почтомат Новая Почта №6168 с. С. Борщ., ул. Героев Небесной Сотни, 20 (маг. Лоток)"
  },
  {
    "id": "123726",
    "name": "6170, Почтомат Новая Почта №6170 ул. Семьи Сосниных, 17 (маг. АТБ)"
  },
  {
    "id": "123727",
    "name": "6173, Почтомат Новая Почта №6173 ул. Ереванская, 30 (маг. Мини Маркет)"
  },
  {
    "id": "123974",
    "name": "6224, Почтомат Новая Почта №6224 бульв. Русановский, 11 (маг. АТБ)"
  },
  {
    "id": "124142",
    "name": "6265, Почтомат Новая Почта №6265 ул. Нагорная, 8/32 (маг. Продукты)"
  },
  {
    "id": "124143",
    "name": "6297, Почтомат Новая Почта №6297 бульв. Дружбы Народов, 16а (маг. Новус)"
  },
  {
    "id": "124144",
    "name": "6298, Почтомат Новая Почта №6298 просп. Валерия Лобановского, 4д (маг. Новус)"
  },
  {
    "id": "124145",
    "name": "6299, Почтомат Новая Почта №6299 ул. Георгия Кирпы, 5 (маг. Новус)"
  },
  {
    "id": "124277",
    "name": "6310, Почтомат Новая Почта №6310 пл. Гостомельская, 1 (маг. Новус)"
  },
  {
    "id": "124278",
    "name": "6311, Почтомат Новая Почта №6311 ул. Ивана Кавалеридзе, 1а (маг. Новус)"
  },
  {
    "id": "124279",
    "name": "6312, Почтомат Новая Почта №6312 ул. Святошинская, 3 (маг. Новус)"
  },
  {
    "id": "124280",
    "name": "6313, Почтомат Новая Почта №6313 ул. Академика Беляшевского, 10 (маг. Новус)"
  },
  {
    "id": "124682",
    "name": "6314, Почтомат Новая Почта №6314 ул. Гната Хоткевича, 1а (маг. Новус)"
  },
  {
    "id": "124683",
    "name": "6315, Почтомат Новая Почта №6315 просп. Броварской, 18д (маг. Новус)"
  },
  {
    "id": "124686",
    "name": "6318, Почтомат Новая Почта №6318 ул. Милославская, 2а (ОККО)"
  },
  {
    "id": "124281",
    "name": "6319, Почтомат Новая Почта №6319 ул. Межигорская, 87а (БЦ Межигорский)"
  },
  {
    "id": "124687",
    "name": "6322, Почтомат Новая Почта №6322 ул. Николайчука, 4 (Ринок)"
  },
  {
    "id": "124688",
    "name": "6323, Почтомат Новая Почта №6323 просп. Степана Бандеры, 23 (ТЦ Городок)"
  },
  {
    "id": "124689",
    "name": "6325, Почтомат Новая Почта №6325 просп. Победы, 49 (Амис)"
  },
  {
    "id": "124690",
    "name": "6326, Почтомат Новая Почта №6326 просп. Победы, 38 (Амис)"
  },
  {
    "id": "124873",
    "name": "6327, Почтомат Новая Почта №6327 бульв. Михаила Котельникова, 26 (Делви)"
  },
  {
    "id": "124691",
    "name": "6328, Почтомат Новая Почта №6328 просп. Николая Бажана, 2 (Амис)"
  },
  {
    "id": "124874",
    "name": "6345, Почтомат Новая Почта №6345 ул. Шевченка, 211 (маг. Софиевка)"
  },
  {
    "id": "124875",
    "name": "6355, Почтомат Новая Почта №6355 ул. Соборная, 146 (маг. АТБ)"
  },
  {
    "id": "125405",
    "name": "6376, Почтомат Новая почта №6376 ул. Оноре де Бальзака, 18/78 (маг. АТБ)"
  },
  {
    "id": "125406",
    "name": "6377, Почтомат Новая почта №6377 ул. Сергея Данченко, 12 (маг. Freshop)"
  },
  {
    "id": "125407",
    "name": "6378, Почтомат Новая почта №6378 ул. Никольско-Слободская, 2б (маг. FRESHOP)"
  },
  {
    "id": "125889",
    "name": "6400, Почтомат Новая Почта №6400 ул. Виноградная, 2 (ОSOCOR RESIDENCE)"
  },
  {
    "id": "125817",
    "name": "6406, Почтомат Новая Почта №6406 ул. Генерала Витрука, 13 (маг. ФУДМАРКЕТ)"
  },
  {
    "id": "124876",
    "name": "6555, Почтомат Новая Почта №6555 просп. Героев Сталинграда, 2/37 (Амис)"
  }
]